serissa/__init__.py
serissa/_version.py
serissa/client.py
serissa/handler.py
serissa/log.py
serissa/message.py
serissa-0.0.3.dist-info/LICENSE
serissa-0.0.3.dist-info/METADATA
serissa-0.0.3.dist-info/WHEEL
serissa-0.0.3.dist-info/top_level.txt
serissa-0.0.3.dist-info/RECORD
