Metadata-Version: 2.1
Name: serissa
Version: 0.0.3
Author-email: Lindasy Zhou <i@lin.moe>
License: Affero General Public License GPL v3 (AGPLv3)
Requires-Python: >=3.7
License-File: LICENSE
Provides-Extra: tests
Requires-Dist: pytest ; extra == 'tests'
Requires-Dist: pytest-asyncio ; extra == 'tests'
Requires-Dist: tox ; extra == 'tests'
